[
  {
    "id": 301,
    "nombre": "Alimento para perro adulto Purina Dog Chow",
    "desc": "Bolsa de 15kg de alimento balanceado para perros adultos marca Purina Dog Chow.",
    "precio": 27651.34,
    "imagen": "",
    "stock": 19,
    "disponible": true,
    "categoria": "Perros",
    "marca": "Purina"
  },
  {
    "id": 302,
    "nombre": "Alimento para perro adulto Pro Plan",
    "desc": "Bolsa de 15kg de alimento balanceado para perros adultos marca Pro Plan.",
    "precio": 24029.8,
    "imagen": "",
    "stock": 19,
    "disponible": true,
    "categoria": "Perros",
    "marca": "Purina"
  },
  {
    "id": 303,
    "nombre": "Alimento para perro adulto Royal Canin",
    "desc": "Bolsa de 15kg de alimento balanceado para perros adultos marca Royal Canin.",
    "precio": 18635.02,
    "imagen": "",
    "stock": 10,
    "disponible": true,
    "categoria": "Perros",
    "marca": "Royal Canin"
  },
  {
    "id": 304,
    "nombre": "Alimento para perro adulto Vitalcan",
    "desc": "Bolsa de 15kg de alimento balanceado para perros adultos marca Vitalcan.",
    "precio": 22829.83,
    "imagen": "",
    "stock": 16,
    "disponible": true,
    "categoria": "Perros",
    "marca": "Vitalcan"
  },
  {
    "id": 305,
    "nombre": "Alimento para perro adulto Sieger",
    "desc": "Bolsa de 15kg de alimento balanceado para perros adultos marca Sieger.",
    "precio": 20280.43,
    "imagen": "",
    "stock": 8,
    "disponible": true,
    "categoria": "Perros",
    "marca": "Sieger"
  },
  {
    "id": 311,
    "nombre": "Alimento para gato adulto Whiskas",
    "desc": "Bolsa de 10kg de alimento balanceado para gatos adultos marca Whiskas.",
    "precio": 18933.22,
    "imagen": "",
    "stock": 18,
    "disponible": true,
    "categoria": "Gatos",
    "marca": "Whiskas"
  },
  {
    "id": 312,
    "nombre": "Alimento para gato adulto Purina Cat Chow",
    "desc": "Bolsa de 10kg de alimento balanceado para gatos adultos marca Purina Cat Chow.",
    "precio": 12445.16,
    "imagen": "",
    "stock": 11,
    "disponible": true,
    "categoria": "Gatos",
    "marca": "Purina"
  },
  {
    "id": 313,
    "nombre": "Alimento para gato adulto Pro Plan",
    "desc": "Bolsa de 10kg de alimento premium para gatos adultos marca Pro Plan.",
    "precio": 39855.72,
    "imagen": "",
    "stock": 8,
    "disponible": true,
    "categoria": "Gatos",
    "marca": "Purina"
  },
  {
    "id": 314,
    "nombre": "Alimento para gato adulto Royal Canin",
    "desc": "Bolsa de 10kg de alimento premium para gatos adultos marca Royal Canin.",
    "precio": 37246.72,
    "imagen": "",
    "stock": 15,
    "disponible": true,
    "categoria": "Gatos",
    "marca": "Royal Canin"
  },
  {
    "id": 315,
    "nombre": "Alimento para gato adulto Vitalcan",
    "desc": "Bolsa de 10kg de alimento premium para gatos adultos marca Vitalcan.",
    "precio": 26965.46,
    "imagen": "",
    "stock": 8,
    "disponible": true,
    "categoria": "Gatos",
    "marca": "Vitalcan"
  },
  {
    "id": 321,
    "nombre": "Alimento para hámsters",
    "desc": "Alimento para hámsters, bolsa 1kg.",
    "precio": 7147.59,
    "imagen": "",
    "stock": 11,
    "disponible": true,
    "categoria": "Hamsters",
    "marca": "Genérico"
  },
  {
    "id": 322,
    "nombre": "Alimento balanceado para conejos jóvenes",
    "desc": "Alimento balanceado para conejos jóvenes, bolsa 1kg.",
    "precio": 4462.36,
    "imagen": "",
    "stock": 10,
    "disponible": true,
    "categoria": "Conejos",
    "marca": "Conejin"
  },
  {
    "id": 323,
    "nombre": "Mix de semillas para pájaros",
    "desc": "Mix de semillas para pájaros, bolsa 1kg.",
    "precio": 6314.23,
    "imagen": "",
    "stock": 8,
    "disponible": true,
    "categoria": "Aves",
    "marca": "Genérico"
  },
  {
    "id": 324,
    "nombre": "Escamas nutritivas para peces tropicales Tetra",
    "desc": "Escamas nutritivas para peces tropicales marca Tetra, bolsa 1kg.",
    "precio": 11466.07,
    "imagen": "",
    "stock": 9,
    "disponible": true,
    "categoria": "Peces",
    "marca": "Tetra"
  },
  {
    "id": 331,
    "nombre": "Cama para perro mediana",
    "desc": "Cama para perro mediana de alta calidad, resistente y cómodo.",
    "precio": 20283.12,
    "imagen": "",
    "stock": 4,
    "disponible": true,
    "categoria": "Accesorios",
    "marca": "AnimalWorld"
  },
  {
    "id": 332,
    "nombre": "Cama para gato tipo iglú",
    "desc": "Cama para gato tipo iglú de alta calidad, resistente y cómodo.",
    "precio": 13891.85,
    "imagen": "",
    "stock": 5,
    "disponible": true,
    "categoria": "Accesorios",
    "marca": "PetPro"
  },
  {
    "id": 333,
    "nombre": "Correa extensible 5m",
    "desc": "Correa extensible 5m de alta calidad, resistente y cómodo.",
    "precio": 14808.81,
    "imagen": "",
    "stock": 5,
    "disponible": true,
    "categoria": "Accesorios",
    "marca": "Petsy"
  },
  {
    "id": 334,
    "nombre": "Collar regulable",
    "desc": "Collar regulable de alta calidad, resistente y cómodo.",
    "precio": 7773.46,
    "imagen": "",
    "stock": 4,
    "disponible": true,
    "categoria": "Accesorios",
    "marca": "Petsy"
  },
  {
    "id": 335,
    "nombre": "Pecera 100L con filtro",
    "desc": "Pecera 100L con filtro de alta calidad, resistente y cómodo.",
    "precio": 17797.08,
    "imagen": "",
    "stock": 11,
    "disponible": true,
    "categoria": "Accesorios",
    "marca": "Mascotaland"
  },
  {
    "id": 336,
    "nombre": "Jaula para canarios",
    "desc": "Jaula para canarios de alta calidad, resistente y cómodo.",
    "precio": 24904.99,
    "imagen": "",
    "stock": 4,
    "disponible": true,
    "categoria": "Accesorios",
    "marca": "Mascotaland"
  },
  {
    "id": 338,
    "nombre": "Transportín rígido",
    "desc": "Transportín rígido de alta calidad, resistente y cómodo.",
    "precio": 34161.01,
    "imagen": "",
    "stock": 3,
    "disponible": true,
    "categoria": "Accesorios",
    "marca": "Peptsy"
  },
  {
    "id": 339,
    "nombre": "Mochila transportadora",
    "desc": "Mochila transportadora de alta calidad, resistente y cómodo.",
    "precio": 48965.38,
    "imagen": "",
    "stock": 10,
    "disponible": true,
    "categoria": "Accesorios",
    "marca": "Petsy"
  },
  {
    "id": 340,
    "nombre": "Rascador con múltiples niveles",
    "desc": "Rascador con múltiples niveles de alta calidad, resistente y cómodo.",
    "precio": 16276.63,
    "imagen": "",
    "stock": 8,
    "disponible": true,
    "categoria": "Accesorios",
    "marca": "Mascotaland"
  },
  {
    "id": 341,
    "nombre": "Arena sanitaria aglomerante",
    "desc": "Arena sanitaria aglomerante para gatos, presentación 8kg.",
    "precio": 10355.99,
    "imagen": "",
    "stock": 13,
    "disponible": true,
    "categoria": "Arenas sanitarias",
    "marca": "Zootec"
  },
  {
    "id": 342,
    "nombre": "Piedritas sanitarias sílice",
    "desc": "Piedritas sanitarias sílice para gatos, presentación 5kg.",
    "precio": 35269.69,
    "imagen": "",
    "stock": 16,
    "disponible": true,
    "categoria": "Arenas sanitarias",
    "marca": "Sanicat"
  },
  {
    "id": 344,
    "nombre": "Arena perfumada con lavanda",
    "desc": "Arena perfumada con lavanda para gatos, presentación 4kg.",
    "precio": 8808.59,
    "imagen": "",
    "stock": 19,
    "disponible": true,
    "categoria": "Arenas sanitarias",
    "marca": "Zootec"
  },
  {
    "id": 345,
    "nombre": "Arena premium ultra absorbente",
    "desc": "Arena premium ultra absorbente para gatos, presentación 11kg.",
    "precio": 17503.19,
    "imagen": "",
    "stock": 12,
    "disponible": true,
    "categoria": "Arenas sanitarias",
    "marca": "Rubicat"
  }
]